README
setup.py
downloader/__init__.py
downloader/memoize.py
downloader/test_downloader.py
downloader_py3.egg-info/PKG-INFO
downloader_py3.egg-info/SOURCES.txt
downloader_py3.egg-info/dependency_links.txt
downloader_py3.egg-info/top_level.txt