Metadata-Version: 1.2
Name: downloader-py3
Version: 1.0.2
Summary: Download URLs using a compressed disk cache and a random throttling interval.
Home-page: https://github.com/ice1995/downloader-py3
Author: Bohan Zhang
Author-email: zhangbohan.dell@gmail.com
License: MIT
Project-URL: Source, https://github.com/gtzampanakis/downloader
Keywords: downloader dwonloader-py3
Platform: Any
Classifier: Programming Language :: Python
Classifier: License :: OSI Approved :: MIT License
Classifier: Operating System :: OS Independent
Classifier: Development Status :: 4 - Beta
Classifier: Intended Audience :: Developers
Classifier: Topic :: Internet :: WWW/HTTP
Classifier: Topic :: Internet :: WWW/HTTP :: Indexing/Search
Requires: lxml (> 3.2.1)
Requires-Python: >=3
